ds_iplookup/__init__.py
ds_iplookup/ip_sources.py
ds_iplookup/iplookup.py
ds_iplookup-0.1.2.dist-info/LICENSE
ds_iplookup-0.1.2.dist-info/METADATA
ds_iplookup-0.1.2.dist-info/WHEEL
ds_iplookup-0.1.2.dist-info/entry_points.txt
ds_iplookup-0.1.2.dist-info/RECORD
