Metadata-Version: 2.3
Name: ds-iplookup
Version: 0.1.2
Summary: IP lookup tool
License: MIT
Author: Danny Stewart
Author-email: danny@stewart.cc
Requires-Python: >=3.12
Classifier: License :: OSI Approved :: MIT License
Classifier: Programming Language :: Python :: 3
Classifier: Programming Language :: Python :: 3.12
Classifier: Programming Language :: Python :: 3.13
Requires-Dist: dsbase (>=0.3.3,<0.4.0)
Requires-Dist: pycountry (>=24.6.1,<25.0.0)
Requires-Dist: requests (>=2.32.3,<3.0.0)
